README.md
setup.py
pyzabbixAll/__init__.py
pyzabbixAll/myzabbix.py
pyzabbixAll/test.py
pyzabbixAll.egg-info/PKG-INFO
pyzabbixAll.egg-info/SOURCES.txt
pyzabbixAll.egg-info/dependency_links.txt
pyzabbixAll.egg-info/requires.txt
pyzabbixAll.egg-info/top_level.txt