Metadata-Version: 2.1
Name: pyzabbixAll
Version: 1.2.1
Summary: pyzabbix模块升级版
Home-page: https://www.haisheng666.xin/user_system/login?next=/robot/
Author: Hanson
Author-email: 821058392@qq.com
License: UNKNOWN
Platform: UNKNOWN
Classifier: Programming Language :: Python :: 3
Classifier: License :: OSI Approved :: MIT License
Classifier: Operating System :: OS Independent
Requires-Python: >=3.7
